Workbook

Sheet Costos
A1: Sueldo Base Mensual | B1: 20000 | D1: Ganacia % | E1: 0.4 | G1: Renta | H1: 24360
A2: Jornada | B2: 9 | D2: Credito | E2: 0.03 | G2: Luz | H2: 1500
A3: Costo por hora | B3: =ROUND((((B1/20)/B2)),1) -> 111.1 | D3: Mora | E3: 0.01 | G3: Agua | H3: 500
A4: Gastos fijos Dia | B4: =(((SUM(H1:H5))/4)/5)/B2 -> 197 | D4: Gasolina | E4: 27 | G4: Internet | H4: 600
D5: Hra Ventas | E5: 125 | G5: Camioneta | H5: 8500
B7: Área | C7: Servicio | D7: Unidad | E7: Valor agregado | F7: Horas | G7: Costo SSEPI | H7: Costo VA
B8: Diseño e ingeniería | C8: Diseño de arquitectura de control, redes, estacones | D8: por hora | E8: =(B3+$B$4) -> 308.1 | F8: 6 | G8: =$B$3*F8 -> 666.6 | H8: =F8*E8 -> 1848.6
C9: Selección de equipos de control y comunicación | D9: por hora | E9: =(B3+$B$4) -> 308.1 | F9: 0 | G9: =$B$3*F9 -> 0 | H9: =F9*E9 -> 0
B10: Eléctrica | C10: Diseño de tablero eléctrico BT | D10: por hora | E10: =($B$3*1.3)+$B$4 -> 341.43 | F10: 0 | G10: =$B$3*F10 -> 0 | H10: =F10*E10 -> 0 | K10: Dias estimados | L10: 1
C11: Fabricación e instalación de tablero BT | D11: por hora | E11: =($B$3*1.2)+$B$4 -> 330.32 | F11: 0 | G11: =$B$3*F11 -> 0 | H11: =F11*E11 -> 0
C12: Instalación de cableado/sensores | D12: por hora | E12: =$B$3 -> 111.1 | F12: 5 | G12: =$B$3*F12 -> 555.5 | H12: =F12*E12 -> 555.5
B13: Control | C13: Programación de rutinas en PLC | D13: por hora | E13: =($B$3+$B$4)*2.1 -> 647.01 | F13: 0 | G13: =$B$3*F13 -> 0 | H13: =F13*E13 -> 0 | K13: Traslados
C14: Creación de interfaz HMI | D14: por hora | E14: =($B$3+$B$4)*2.1 -> 647.01 | G14: =$B$3*F14 -> 0 | H14: =F14*E14 -> 0 | K14: Viaticos
C15: Configuración de servomotores y sistemas de posicionamiento | D15: por hora | E15: =($B$3+$B$4)*2.3 -> 708.63 | F15: 0 | G15: =$B$3*F15 -> 0 | H15: =F15*E15 -> 0 | K15: Hospeddaje
C16: Programación de variadores de velocidad (VFD) | D16: por hora | E16: =($B$3+$B$4)*2.2 -> 677.82 | G16: =$B$3*F16 -> 0 | H16: =F16*E16 -> 0 | K16: Costos Automatización | L16: =H25 -> 8131.955
B17: Diseño mecánico | C17: Modelado 3D de herramental | D17: por modelo | E17: =($B$3+$B$4)*2.5 -> 770.25 | F17: 5 | G17: =$B$3*F17 -> 555.5 | H17: =F17*E17 -> 3851.25 | K17: Costos Dany | L17: 291
B18: Siatemas de visión | C18: Lectura y validación de códigos QR, Datamatrix, OCR, etc | D18: por hora | E18: =($B$3+$B$4)*2.5 -> 770.25 | G18: =$B$3*F18 -> 0 | H18: =F18*E18 -> 0 | K18: Subtotal | L18: =SUM(L13:L17) -> 8422.955
C19: Integración de cámaras industriales, sensores de visión | D19: por hora | E19: =($B$3+$B$4)*2.5 -> 770.25 | G19: =$B$3*F19 -> 0 | H19: =F19*E19 -> 0 | K19: Total | L19: =L18*1.03 -> 8675.6437
C20: Trazabilidad y registro de producción | D20: por hora | E20: =($B$3+$B$4)*2.5 -> 770.25 | G20: =$B$3*F20 -> 0 | H20: =F20*E20 -> 0
B21: Soporte | C21: Diagnóstico de fallas en sistemas de automatización | D21: por hora | E21: =B3*10 -> 1111 | G21: =$B$3*F21 -> 0 | H21: =F21*E21 -> 0
C22: Optimización de tiempos de ciclo, velocidades y eficiencia | D22: por hora | E22: =$B$3*10 -> 1111 | G22: =$B$3*F22 -> 0 | H22: =F22*E22 -> 0
C23: Respaldo, control de versiones y documentación de programas | D23: por hora | E23: =$B$3*3 -> 333.3 | G23: =$B$3*F23 -> 0 | H23: =F23*E23 -> 0
C24: Capacitación a personal operativo y técnico | D24: por hora | E24: =$B$3*8 -> 888.8 | F24: 0 | G24: =$B$3*F24 -> 0 | H24: =F24*E24 -> 0
E25: Subtotal: | G25: =SUM(G8:G24) -> 1777.6 | H25: =SUM(H8:H24)*1.3 -> 8131.955
E26: Total:
B27: GASTOS VENTAS
B29: EMPRESA | C29: KM | D29: Litos De cosnumo | E29: COSTO GASOLINA | F29: Hras | G29: Costo Ventas | H29: Costo Total
B30: BOLSAS DE LOS ALTOS | C30: 226 | D30: =C30/9.5 -> 23.789474 | E30: =D30*$E$4 -> 642.31579 | F30: 5 | G30: =F30*$E$5 -> 625 | H30: =E30+G30 -> 1267.3158
B31: ANGUIPALST | C31: 234 | D31: =C31/9.5 -> 24.631579 | E31: =D31*$E$4 -> 665.05263 | F31: 6 | G31: =F31*$E$5 -> 750 | H31: =E31+G31 -> 1415.0526
B32: ECOBOLSAS | C32: 216 | D32: =C32/9.5 -> 22.736842 | E32: =D32*$E$4 -> 613.89474 | F32: 5 | G32: =F32*$E$5 -> 625 | H32: =E32+G32 -> 1238.8947
B33: BADER TABACHINES | C33: 17.2 | D33: =C33/9.5 -> 1.8105263 | E33: =D33*$E$4 -> 48.884211 | F33: 2 | G33: =F33*$E$5 -> 250 | H33: =E33+G33 -> 298.88421
B34: BODYCOTE | C34: 90.6 | D34: =C34/9.5 -> 9.5368421 | E34: =D34*$E$4 -> 257.49474 | F34: 3 | G34: =F34*$E$5 -> 375 | H34: =E34+G34 -> 632.49474
B35: COFICAB | C35: 80 | D35: =C35/9.5 -> 8.4210526 | E35: =D35*$E$4 -> 227.36842 | F35: 3 | G35: =F35*$E$5 -> 375 | H35: =E35+G35 -> 602.36842
B36: CONDUMEX | C36: 90.6 | D36: =C36/9.5 -> 9.5368421 | E36: =D36*$E$4 -> 257.49474 | F36: 3 | G36: =F36*$E$5 -> 375 | H36: =E36+G36 -> 632.49474
B37: ECSA | C37: 32 | D37: =C37/9.5 -> 3.3684211 | E37: =D37*$E$4 -> 90.947368 | F37: 2 | G37: =F37*$E$5 -> 250 | H37: =E37+G37 -> 340.94737
B38: EMMSA | C38: 21.6 | D38: =C38/9.5 -> 2.2736842 | E38: =D38*$E$4 -> 61.389474 | F38: 2 | G38: =F38*$E$5 -> 250 | H38: =E38+G38 -> 311.38947
B39: EPC 1 | C39: 400 | D39: =C39/9.5 -> 42.105263 | E39: =D39*$E$4 -> 1136.8421 | F39: 7 | G39: =F39*$E$5 -> 875 | H39: =E39+G39 -> 2011.8421
B40: EPC 2 | C40: 402 | D40: =C40/9.5 -> 42.315789 | E40: =D40*$E$4 -> 1142.5263 | F40: 8 | G40: =F40*$E$5 -> 1000 | H40: =E40+G40 -> 2142.5263
B41: FRAENKISCHE | C41: 79.4 | D41: =C41/9.5 -> 8.3578947 | E41: =D41*$E$4 -> 225.66316 | F41: 3 | G41: =F41*$E$5 -> 375 | H41: =E41+G41 -> 600.66316
... B61: MINO INDUSTRY | C61: 29.2 | D61: =C61/9.5 -> 3.0736842 | E61: =D61*$E$4 -> 82.989474 | F61: 2 | G61: =F61*$E$5 -> 250 | H61: =E61+G61 -> 332.98947

Sheet Materiales
G1: Ganacia % | H1: 1.3
A4: Item | B4: Cantidad | C4: Modelo | D4: Descripcion | E4: C/U | F4: Link | G4: Tiempo de Entrega | H4: Importe | I4: Precios SSEPI
A5: 1 | B5: 1 | D5: Base de con resorte para encoder de medida | E5: 3000 | F5: https://articulo.mercadolibre.com.mx/MLM-1393795990-soporte-encoder-medidor-distancia-encoder-20mm-plc-arduino-_JM#intervention_type=full&position=2&search_layout=grid&type=cart_intervention&tracking_id=71ce98cf-33b2-4d6d-a7d7-1a7511312ac2 | G5: 3 - 4 dias | H5: =E5*B5 -> 3000 | I5: =H5*$H$1 -> 3900
A6: 2 | B6: 1 | D6: Rueda de medida de encoder | E6: 200 | F6: https://www.amazon.com.mx/Luejnbogty-medici%C3%B3n-industrial-codificador-accesorios/dp/B0F12DBXWQ/ref=sr_1_1?__mk_es_MX=%C3%85M%C3%85%C5%BD%C3%95%C3%91&crid=1CR5QPDETNF4Z&dib=eyJ2IjoiMSJ9.kGPoBSkjoGUtn9CBqV5bxPOtlLhbIqk_yar3iIkmP5UcIO5Tu7kC_ycdi4_sXBCn3KMynVQGpQODhhedu-Y-BNy5YJi_DJpAEEVY6MAdBQvpP4jXCn8LtzZgtd3JTDalZnZ4xyc2Ro0ZTtI6b9yxZApRS_LehxFGg4g93g7Qqez-Wi0huYJqTGrYy5EfqdsUCOJ2NfCA7UK3VbyzNPHND7ohiyDsQHqMjO6M01ux1PE.UeyFOxMECi2HzalIj1__U3rKabuRhFW_8xVRooxqLqU&dib_tag=se&keywords=Encoder%2Bde%2Bmedici%C3%B3n%2Bde%2Bgoma%2Bde%2Baluminio%2Bindustrial%2Bde%2B360%2Bmm%2Bx%2B8%2Bmm%2Bx%2B15%2Bmm&qid=1768341890&s=tools&sprefix=encoder%2Bde%2Bmedici%C3%B3n%2Bde%2Bgoma%2Bde%2Baluminio%2Bindustrial%2Bde%2B360%2Bmm%2Bx%2B8%2Bmm%2Bx%2B15%2Bmm%2Chi%2C159&sr=1-1&ufe=app_do%3Aamzn1.fos.de93fa6a-174c-4df7-be7c-5bc8e9c5a71b&th=1 | G6: 3 - 4 dias | H6: =E6*B6 -> 200 | I6: =H6*$H$1 -> 260
A7: 3 | B7: 1 | D7: SSoporte, perfil de aluminio 45x45mm para base de encoder | E7: 1860 | F7: https://www.amazon.com.mx/montaje-perfiles-extrusi%C3%B3n-aluminio-calibre/dp/B0BJZW9H1J | G7: 3-4 días | H7: =E7*B7 -> 1860 | I7: =H7*$H$1 -> 2418
A8: 4 | B8: 1 | D8: Tornilleria para fijacion y ensamble | E8: 500 | H8: =E8*B8 -> 500 | I8: =H8*$H$1 -> 650
A9: 5 | B9: 4 | D9: Barrenanclas 3/8" | E9: 30 | F9: https://craftqube.mx/products/escuadra-45x45-bosch-rexroth | H9: =E9*B9 -> 120 | I9: =H9*$H$1 -> 156
A10: 6 | B10: 1 | D10: Escuadras para perfil de aluminio 45 x45 | E10: 100 | F10: https://articulo.mercadolibre.com.mx/MLM-769941921-escuadra-esquina-para-perfil-de-aluminio-estructural-4545-_JM?matt_tool=28238160&utm_source=google_shopping&utm_medium=organic | H10: =E10*B10 -> 100 | I10: =H10*$H$1 -> 130
A11: 7 | B11: 4 | D11: Tubo Conduit 1/2" pared delgada (1 mm), et. verde, 3 m | E11: 105 | F11: https://www.fixferreterias.com/tubo-conduit-1-2-galvanizado-3-m-pared-delgada-et-verde.html | G11: 3-4 dias | H11: =E11*B11 -> 420 | I11: =H11*$H$1 -> 546
A12: 8 | B12: 5 | D12: Codos etiqueta verde de 1/2" | E12: 26.8 | F12: https://www.mercadolibre.com.mx/5-pzs-codo-ptubo-electrico-conduit-12-pared-delgada-argos/up/MLMU3220826280#polycard_client=search-desktop&search_layout=grid&position=6&type=product&tracking_id=323369b6-ca59-4db1-a301-2bed088fad1e&wid=MLM2330687131&sid=search | G12: 3-4 dias | H12: =E12*B12 -> 134 | I12: =H12*$H$1 -> 174.2
A13: 9 | B13: 10 | D13: Cople Tipo Americano Pared Delgada 1/2 " | E13: 10 | F13: https://www.mercadolibre.com.mx/10-pzs-cople-tipo-americano-pared-delgada-12-pulgada-argos/up/MLMU3221255460#polycard_client=search-desktop&search_layout=grid&position=5&type=product&tracking_id=8e838bd8-220b-48bb-86e7-74d7d2d8f1e0&wid=MLM2330919125&sid=search | G13: 6 dias | H13: =E13*B13 -> 100 | I13: =H13*$H$1 -> 130
A14: 10 | B14: 5 | D14: Conector Conduit 1/2" | E14: 20 | F14: https://articulo.mercadolibre.com.mx/MLM-3261640688-conector-conduit-pared-delgada-acero-galvanizado-12-5-pzas-_JM#polycard_client=search-desktop&search_layout=grid&position=12&type=item&tracking_id=dbbea721-7382-4a75-937a-5cb86d5b408f&wid=MLM3261640688&sid=search | G14: 6 dias | H14: =E14*B14 -> 100 | I14: =H14*$H$1 -> 130
A15: 11 | B15: 1 | D15: Caja De Registro Estanca IP55 8x8x4.5 | E15: 85 | F15: https://www.mercadolibre.com.mx/caja-de-registro-estanca-ip55-8x8x45-sin-conos/up/MLMU983580995#polycard_client=search-desktop&search_layout=grid&position=31&type=product&tracking_id=c04a1414-b3f3-4917-9914-aeaf7e5e5abe&wid=MLM725921615&sid=search | G15: 5 dias | H15: =E15*B15 -> 85 | I15: =H15*$H$1 -> 110.5
A16: 12 | B16: 10 | D16: Metros cable control 5 x 20 awg 0.50mm2 | E16: 50 | F16: https://dimeint.com/products/arco5x20 | G16: 4 dias | H16: =E16*B16 -> 500 | I16: =H16*$H$1 -> 650
A17: 13 | B17: 1 | D17: Riel unicanal | E17: 183.26 | F17: https://www.elektron.com.mx/perfil-unicanal-solido-4-x-2-calibre-16-use-4x2-omega | G17: 6 dias | H17: =E17*B17 -> 183.26 | I17: =H17*$H$1 -> 238.238
A18: 14 | B18: 7 | D18: Abrazaderas unicanal | E18: 10 | F18: https://www.elektron.com.mx/abrazadera-unicanal-1-2-para-conduit-pared-delgada-aw-12-anclo | G18: 6 dias | H18: =E18*B18 -> 70 | I18: =H18*$H$1 -> 91
A19: 15 | B19: 14 | D19: Taquete arpon 1/4X2-1/4 | E19: 6 | F19: https://eltornillo.com.mx/tienda-en-linea/catalogo/taquetes/taquete-arpon-galvanizado-1%2F4x2_1%2F4?gad_source=1&gad_campaignid=21686270870&gbraid=0AAAAADsHgckfzLBgZqtF2UWg0tSxne_Eq | G19: 2 dias | H19: =E19*B19 -> 84 | I19: =H19*$H$1 -> 109.2
A20: 16 | B20: 10 | D20: Conector Rapido Cableado Electrico 28-12 Awg 1 Via | E20: 14.5 | F20: https://articulo.mercadolibre.com.mx/MLM-4253948562-10-piezas-conector-rapido-cableado-electrico-28-12-awg-1-via-_JM#polycard_client=search-desktop&search_layout=grid&position=2&type=item&tracking_id=d8e4ec02-3de4-4fe4-99b5-87802ee8790e&wid=MLM4253948562&sid=search | G20: 2 dias | H20: =E20*B20 -> 145 | I20: =H20*$H$1 -> 188.5
A21: 17 | B21: 1 | D21: Cople etiqueta amarilla 1/2" | E21: 10 | H21: =E21*B21 -> 10 | I21: =H21*$H$1 -> 13
A22: 18 | H22: =E22*B22 -> 0 | I22: =H22*$H$1 -> 0
A23: 19 | H23: =E23*B23 -> 0 | I23: =H23*$H$1 -> 0
I24: =H24*$H$1 -> 0
G25: Total | H25: =SUM(H5:H23) -> 7611.26 | I25: =SUM(I5:I23) -> 9894.638

Sheet Cotizacion
D6: FOLIO: SP-A260121 | G6: =TODAY() -> 46049 | L6: =D6 -> FOLIO: SP-A260121 | O6: =TODAY() -> 46049
D7: CLIENTE: | E7: Serviacero Comercial | L7: CLIENTE: | M7: =E7 -> Serviacero Comercial
D8: DIRECCIÓN: | E8: Cto. Oleoducto 212, Ciudad Industrial, 37490 León de los Aldama, Gto. | L8: DIRECCIÓN: | M8: =E8 -> Cto. Oleoducto 212, Ciudad Industrial, 37490 León de los Aldama, Gto.
D10: CONTACTO: | E10: Ing. Alejandro Bocanegra | L10: CONTACTO: | M10: =E10 -> Ing. Alejandro Bocanegra
D11: CORREO: | L11: CORREO:
D12: TELEFONO: | L12: TELEFONO:
A13: CANT. | B13: DESCRIPCIÓN | G13: C/U | H13: IMPORTE | I13: Archivos Adjuntos:
B14: Suministro de Material | G14: =Materiales!I25 -> 9894.638 | H14: =G14 -> 9894.638
A15: =Materiales!B5 -> 1 | B15: =Materiales!D5 -> Base de con resorte para encoder de medida
A16: =Materiales!B6 -> 1 | B16: =Materiales!D6 -> Rueda de medida de encoder
A17: =Materiales!B7 -> 1 | B17: =Materiales!D7 -> SSoporte, perfil de aluminio 45x45mm para base de encoder
A18: =Materiales!B8 -> 1 | B18: =Materiales!D8 -> Tornilleria para fijacion y ensamble
A19: =Materiales!B9 -> 4 | B19: =Materiales!D9 -> Barrenanclas 3/8"
A20: =Materiales!B10 -> 1 | B20: =Materiales!D10 -> Escuadras para perfil de aluminio 45 x45
A21: =Materiales!B11 -> 4 | B21: =Materiales!D11 -> Tubo Conduit 1/2" pared delgada (1 mm), et. verde, 3 m
A22: =Materiales!B12 -> 5 | B22: =Materiales!D12 -> Codos etiqueta verde de 1/2"
A23: =Materiales!B13 -> 10 | B23: =Materiales!D13 -> Cople Tipo Americano Pared Delgada 1/2 "
A24: =Materiales!B14 -> 5 | B24: =Materiales!D14 -> Conector Conduit 1/2"
A25: =Materiales!B15 -> 1 | B25: =Materiales!D15 -> Caja De Registro Estanca IP55 8x8x4.5
A26: =Materiales!B16 -> 10 | B26: =Materiales!D16 -> Metros cable control 5 x 20 awg 0.50mm2
... A31: =Materiales!B21 -> 1 | B31: =Materiales!D21 -> Cople etiqueta amarilla 1/2"
B32: Actividades a Realizar
B33: Diseño, fabricación y ensablado de soporte para encoder E500-3-T-24 AUTONICS | G33: =Costos!L19 -> 8675.6437 | H33: =G33 -> 8675.6437
B35: Montaje de soporte en planta
B36: Instlación de tuberia y ruteo de cable
A37: POLITICAS: | G37: SUBTOTAL | H37: =SUM(H14:H36) -> 18570.282
A38: Condiciones de pago: 50% de anticipo, 50% al terminar el trabajo | G38: IVA 16% | H38: =H37*0.16 -> 2971.2451
A39: Vigencia: 05 DÍAS HÁBILES.
A40: Precio en MONEDA NACIONAL.
A41: Se requiere ÓRDEN DE COMPRA para iniciar el servicio. | G41: TOTAL | H41: =SUM(H37:H40) -> 21541.527
A42: Después de confirmado el servicio NO SE ACEPTAN CANCELACIONES.
A43: NOTAS IMPORTANTES:
A44: Para Mayor Información, consulte losterminos y condiciones en: https://www.ssepi.org/terms
A46: Tiempo de entrega de material 5-6 Días Hábiles. Montaje 4 Horas en planta
A48: Ing. Daniel Zuñiga | D48: ventas@ssepi.org | G48: 477 737 3118
